StackGP/StackGP.py
StackGP/__init__.py
stackgp-0.0.14.dist-info/licenses/LICENSE
stackgp-0.0.14.dist-info/METADATA
stackgp-0.0.14.dist-info/WHEEL
stackgp-0.0.14.dist-info/top_level.txt
stackgp-0.0.14.dist-info/RECORD
