Metadata-Version: 2.4
Name: StackGP
Version: 0.0.14
Summary: A stack-based genetic programming system
Author-email: Nathan Haut <hautnath@msu.edu>
Project-URL: Homepage, https://github.com/hoolagans/StackGP
Project-URL: Issues, https://github.com/hoolagans/StackGP/issues
Classifier: Programming Language :: Python :: 3
Classifier: License :: OSI Approved :: MIT License
Classifier: Operating System :: OS Independent
Requires-Python: >=3.8
License-File: LICENSE
Requires-Dist: dill
Requires-Dist: numpy
Requires-Dist: matplotlib
Requires-Dist: scipy
Requires-Dist: scikit-learn
Requires-Dist: sympy
Dynamic: license-file
